examples/demo_distilgpt2.py
examples/simple_example.py
tinyedgellm/__init__.py
tinyedgellm/advanced_quantization.py
tinyedgellm/benchmarking.py
tinyedgellm/deployment.py
tinyedgellm/knowledge_distillation.py
tinyedgellm/pruning.py
tinyedgellm/quantization.py
tinyedgellm/structured_pruning.py
tinyedgellm-0.1.0.dist-info/licenses/LICENSE
tinyedgellm-0.1.0.dist-info/METADATA
tinyedgellm-0.1.0.dist-info/WHEEL
tinyedgellm-0.1.0.dist-info/top_level.txt
tinyedgellm-0.1.0.dist-info/RECORD
