Metadata-Version: 2.4
Name: tinyedgellm
Version: 0.1.0
Summary: A modular framework for LLM quantization, structured pruning, and edge deployment
Home-page: https://github.com/krish567366/tinyedgellm
Author: Krishna Bajpai, Vedanshi Gupta
Author-email: Krishna Bajpai <krishna@krishnabajpai.me>, Vedanshi Gupta <vedanshigupta158@gmail.com>
Maintainer-email: Krishna Bajpai <krishna@krishnabajpai.me>
License: MIT
Project-URL: Homepage, https://github.com/krish567366/tinyedgellm
Project-URL: Documentation, https://krish567366.github.io/tinyedgellm/
Project-URL: Repository, https://github.com/krish567366/tinyedgellm
Project-URL: Issues, https://github.com/krish567366/tinyedgellm/issues
Project-URL: Changelog, https://github.com/krish567366/tinyedgellm/blob/main/CHANGELOG.md
Keywords: llm,quantization,pruning,compression,edge-computing,machine-learning,transformers
Classifier: Development Status :: 3 - Alpha
Classifier: Intended Audience :: Developers
Classifier: Intended Audience :: Science/Research
Classifier: License :: OSI Approved :: MIT License
Classifier: Operating System :: OS Independent
Classifier: Programming Language :: Python :: 3
Classifier: Programming Language :: Python :: 3.8
Classifier: Programming Language :: Python :: 3.9
Classifier: Programming Language :: Python :: 3.10
Classifier: Programming Language :: Python :: 3.11
Classifier: Programming Language :: Python :: 3.12
Classifier: Programming Language :: Python :: 3.13
Classifier: Topic :: Scientific/Engineering :: Artificial Intelligence
Classifier: Topic :: Software Development :: Libraries :: Python Modules
Requires-Python: >=3.8
License-File: LICENSE
Requires-Dist: torch>=2.0.0
Requires-Dist: transformers>=4.20.0
Requires-Dist: onnxruntime>=1.14.0
Requires-Dist: bitsandbytes>=0.41.0
Requires-Dist: numpy>=1.21.0
Requires-Dist: scipy>=1.7.0
Requires-Dist: tqdm>=4.64.0
Requires-Dist: psutil>=5.8.0
Requires-Dist: accelerate>=0.20.0
Provides-Extra: dev
Requires-Dist: pytest>=7.0.0; extra == "dev"
Requires-Dist: black>=22.0.0; extra == "dev"
Requires-Dist: flake8>=4.0.0; extra == "dev"
Requires-Dist: mypy>=0.950; extra == "dev"
Provides-Extra: docs
Requires-Dist: mkdocs>=1.5.0; extra == "docs"
Requires-Dist: mkdocs-material>=9.0.0; extra == "docs"
Requires-Dist: mkdocs-git-revision-date-localized-plugin>=1.2.0; extra == "docs"
Requires-Dist: mkdocs-git-committers-plugin-2>=2.2.0; extra == "docs"
Requires-Dist: mkdocs-minify-plugin>=0.8.0; extra == "docs"
Requires-Dist: pymdown-extensions>=10.0.0; extra == "docs"
Provides-Extra: tflite
Requires-Dist: tflite-runtime>=2.11.0; extra == "tflite"
Dynamic: author
Dynamic: home-page
Dynamic: license-file
Dynamic: requires-python
